tests/__init__.py
tests/test_twitter.py
twitter_timeline_rss/__init__.py
twitter_timeline_rss/cli.py
twitter_timeline_rss/settings.py
twitter_timeline_rss/twitter.py
twitter_timeline_rss-1.1.1.dist-info/LICENSE
twitter_timeline_rss-1.1.1.dist-info/METADATA
twitter_timeline_rss-1.1.1.dist-info/WHEEL
twitter_timeline_rss-1.1.1.dist-info/entry_points.txt
twitter_timeline_rss-1.1.1.dist-info/top_level.txt
twitter_timeline_rss-1.1.1.dist-info/zip-safe
twitter_timeline_rss-1.1.1.dist-info/RECORD
