Metadata-Version: 2.1
Name: twitter-timeline-rss
Version: 1.1.1
Summary: Ingest a twitter timeline and render as RSS
Home-page: https://github.com/narfman0/twitter-timeline-rss
Author: Jon Robison
Author-email: narfman0@gmail.com
License: LICENSE
Keywords: twitter timeline rss atom flask
Platform: UNKNOWN
Classifier: Development Status :: 4 - Beta
Classifier: License :: OSI Approved :: GNU General Public License v3 (GPLv3)
Classifier: Operating System :: OS Independent
Classifier: Programming Language :: Python
Classifier: Topic :: Software Development :: Libraries :: Python Modules
Requires-Dist: tweepy
Requires-Dist: flask
